cloudshell/__init__.py
cloudshell/cp/__init__.py
cloudshell/cp/openstack/__init__.py
cloudshell/cp/openstack/constants.py
cloudshell/cp/openstack/exceptions.py
cloudshell/cp/openstack/resource_config.py
cloudshell/cp/openstack/flows/__init__.py
cloudshell/cp/openstack/flows/connectivity_flow.py
cloudshell/cp/openstack/flows/delete_instance_flow.py
cloudshell/cp/openstack/flows/get_console.py
cloudshell/cp/openstack/flows/power_flow.py
cloudshell/cp/openstack/flows/refresh_ip_flow.py
cloudshell/cp/openstack/flows/save_restore_app.py
cloudshell/cp/openstack/flows/vm_details.py
cloudshell/cp/openstack/flows/deploy_vm/__init__.py
cloudshell/cp/openstack/flows/deploy_vm/deploy_app_from_nova_img.py
cloudshell/cp/openstack/models/__init__.py
cloudshell/cp/openstack/models/attr_names.py
cloudshell/cp/openstack/models/connectivity_models.py
cloudshell/cp/openstack/models/deploy_app.py
cloudshell/cp/openstack/models/deployed_app.py
cloudshell/cp/openstack/os_api/__init__.py
cloudshell/cp/openstack/os_api/api.py
cloudshell/cp/openstack/os_api/commands/__init__.py
cloudshell/cp/openstack/os_api/commands/create_floating_ip.py
cloudshell/cp/openstack/os_api/commands/create_instance.py
cloudshell/cp/openstack/os_api/commands/create_security_group.py
cloudshell/cp/openstack/os_api/commands/rollback.py
cloudshell/cp/openstack/os_api/models/__init__.py
cloudshell/cp/openstack/os_api/models/flavor.py
cloudshell/cp/openstack/os_api/models/floating_ip.py
cloudshell/cp/openstack/os_api/models/image.py
cloudshell/cp/openstack/os_api/models/instance.py
cloudshell/cp/openstack/os_api/models/network.py
cloudshell/cp/openstack/os_api/models/port.py
cloudshell/cp/openstack/os_api/models/security_group.py
cloudshell/cp/openstack/os_api/models/subnet.py
cloudshell/cp/openstack/os_api/models/trunk.py
cloudshell/cp/openstack/os_api/services/__init__.py
cloudshell/cp/openstack/os_api/services/validator.py
cloudshell/cp/openstack/os_api/services/vm_details_provider.py
cloudshell_cp_openstack-4.0.1.dist-info/METADATA
cloudshell_cp_openstack-4.0.1.dist-info/WHEEL
cloudshell_cp_openstack-4.0.1.dist-info/top_level.txt
cloudshell_cp_openstack-4.0.1.dist-info/RECORD
