Metadata-Version: 2.1
Name: cloudshell-cp-openstack
Version: 4.0.1
Summary: CloudShell Cloud Provider OpenStack package
Home-page: http://www.qualisystems.com/
Author: QualiSystems
Author-email: info@qualisystems.com
Requires-Python: ~=3.7
Requires-Dist: cloudshell-cp-core (~=2.5)
Requires-Dist: cloudshell-shell-standards (~=1.1)
Requires-Dist: cloudshell-shell-core (~=5.0)
Requires-Dist: cloudshell-shell-connectivity-flow (~=3.1)
Requires-Dist: pydantic (~=1.7)
Requires-Dist: python-keystoneclient (~=4.1)
Requires-Dist: python-novaclient (~=17.2)
Requires-Dist: python-neutronclient (~=7.2)
Requires-Dist: python-glanceclient (~=3.0)
Requires-Dist: jsonpickle (~=1.4)
Requires-Dist: keystoneauth1 (~=4.2)
Requires-Dist: attrs (<23.0,>=21.3)
